llm_fragments_zohoticket.py
llm_fragments_zohoticket-0.4.dist-info/licenses/LICENSE
llm_fragments_zohoticket-0.4.dist-info/METADATA
llm_fragments_zohoticket-0.4.dist-info/WHEEL
llm_fragments_zohoticket-0.4.dist-info/entry_points.txt
llm_fragments_zohoticket-0.4.dist-info/top_level.txt
llm_fragments_zohoticket-0.4.dist-info/RECORD
