Metadata-Version: 2.4
Name: llm-fragments-zohoticket
Version: 0.4
Summary: LLM Fragment Loader for pulling ticket conversations from Zoho Desk
Author: dents-shape
License-Expression: MIT
Project-URL: Homepage, https://github.com/dents-shape/llm-fragments-zohoticket
Project-URL: Issues, https://github.com/dents-shape/llm-fragments-zohoticket/issues
Requires-Python: >=3.9
License-File: LICENSE
Requires-Dist: llm>=0.24
Dynamic: license-file
